skfobserver/__init__.py
skfobserver/client.py
skfobserver/constants.py
skfobserver/hierarchy_models.py
skfobserver/machine_models.py
skfobserver-0.1.43.dist-info/licenses/LICENSE
skfobserver-0.1.43.dist-info/METADATA
skfobserver-0.1.43.dist-info/WHEEL
skfobserver-0.1.43.dist-info/top_level.txt
skfobserver-0.1.43.dist-info/RECORD
