Metadata-Version: 2.4
Name: skfobserver
Version: 0.1.43
Summary: A Python client library for easy integration with the SKF Observer API.
License: MIT License
Project-URL: Documentation, https://www.skf.com/us/products/condition-monitoring-systems/software/aptitude-observer
Keywords: skf,observer,api,client,sdk,data,industrial
Classifier: Programming Language :: Python :: 3.10
Classifier: Programming Language :: Python :: 3.11
Classifier: Programming Language :: Python :: 3.12
Classifier: License :: OSI Approved :: MIT License
Classifier: Operating System :: OS Independent
Classifier: Development Status :: 3 - Alpha
Classifier: Intended Audience :: Developers
Requires-Python: >=3.8
License-File: LICENSE
Requires-Dist: requests>=2.25.1
Dynamic: license-file
